casa_cube/__init__.py
casa_cube/cube.py
casa_cube/molex.py
casa_cube-0.1.0.dist-info/licenses/LICENSE
casa_cube-0.1.0.dist-info/METADATA
casa_cube-0.1.0.dist-info/WHEEL
casa_cube-0.1.0.dist-info/top_level.txt
casa_cube-0.1.0.dist-info/RECORD
