Metadata-Version: 2.4
Name: casa_cube
Version: 0.1.0
Summary: Package to plot data cube from CASA in Python
Home-page: http://github.com/cpinte/casa_cube
Author: Christophe Pinte
Author-email: Christophe Pinte <christophe.pinte@univ-grenoble-alpes.fr>
License: MIT
Project-URL: Homepage, http://github.com/cpinte/casa_cube
Project-URL: Repository, http://github.com/cpinte/casa_cube.git
Keywords: astronomy,CASA,data-cube,visualization
Classifier: Development Status :: 3 - Alpha
Classifier: Intended Audience :: Science/Research
Classifier: License :: OSI Approved :: MIT License
Classifier: Programming Language :: Python :: 3
Classifier: Programming Language :: Python :: 3.6
Classifier: Programming Language :: Python :: 3.7
Classifier: Programming Language :: Python :: 3.8
Classifier: Programming Language :: Python :: 3.9
Classifier: Topic :: Scientific/Engineering :: Astronomy
Requires-Python: >=3.6
License-File: LICENSE
Requires-Dist: numpy
Requires-Dist: matplotlib
Requires-Dist: astropy
Dynamic: author
Dynamic: home-page
Dynamic: license-file
